README.rst
setup.py
lib/evasion/__init__.py
lib/evasion/messenger/__init__.py
lib/evasion/messenger/endpoint.py
lib/evasion/messenger/frames.py
lib/evasion/messenger/hub.py
lib/evasion/messenger/testing.py
lib/evasion/messenger/testing/__init__.py
lib/evasion/messenger/testing/withhub.py
lib/evasion/messenger/tests/__init__.py
lib/evasion/messenger/tests/testmessenger.py
lib/evasion_messenger.egg-info/PKG-INFO
lib/evasion_messenger.egg-info/SOURCES.txt
lib/evasion_messenger.egg-info/dependency_links.txt
lib/evasion_messenger.egg-info/eager_resources.txt
lib/evasion_messenger.egg-info/entry_points.txt
lib/evasion_messenger.egg-info/namespace_packages.txt
lib/evasion_messenger.egg-info/not-zip-safe
lib/evasion_messenger.egg-info/requires.txt
lib/evasion_messenger.egg-info/top_level.txt