Metadata-Version: 1.0
Name: evasion-messenger
Version: 1.2.0
Summary: Messaging library used to package and delivery events
Home-page: UNKNOWN
Author: Oisin Mulvihill
Author-email: oisinmulvihill at gmail dot com
License: Evasion Project CDDL License
Platform: UNKNOWN
